Metadata-Version: 2.1
Name: nezur
Version: 0.1
Summary: A sleek Hash/Encryption management process
